[
  {
    "id": "product_a",
    "name": "SmartAssist Pro（AI業務効率化SaaS）",
    "category": "SaaS / AI",
    "summary": "中小企業向けのAI搭載業務自動化プラットフォーム。議事録自動作成、日報AI生成、タスク自動仕分けなど、社内業務を横断的に効率化。",
    "strengths": [
      "導入初日から使える直感的UI",
      "既存のSlack / Teams / Google Workspaceと完全連携",
      "AI学習により使うほど精度が上がる独自エンジン",
      "月額1人あたり980円〜の圧倒的コストパフォーマンス"
    ],
    "targetCustomer": "従業員30〜300名規模の中小・中堅企業。特にバックオフィスや管理部門の人手不足に悩む企業。",
    "pricing": "月額980円/人（スタンダード）、月額2,480円/人（プロ）、エンタープライズは個別見積り",
    "caseStudies": [
      "製造業A社（従業員80名）：導入3ヶ月で月間120時間の事務工数を削減。営業部門の日報提出率が40%→95%に劇的改善。",
      "IT企業B社（従業員150名）：議事録作成の自動化により、会議後のフォロー速度が平均2日→30分に短縮。"
    ],
    "differentiator": "競合製品（Notion AI、Copilot等）との最大の違いは『日本語の業務文脈への特化』と『中小企業の予算感に合った価格設計』。大企業向けの高額ツールと異なり、ITリテラシーが高くない現場でもすぐ活用できる。"
  },
  {
    "id": "product_b",
    "name": "MediTrack X（医療機器トレーサビリティシステム）",
    "category": "医療 / IoT",
    "summary": "医療機器の流通・使用・廃棄までをIoTセンサーとクラウドで一元管理するトレーサビリティプラットフォーム。法規制対応とコスト最適化を同時に実現。",
    "strengths": [
      "薬機法・UDI規制に完全準拠したコンプライアンス設計",
      "RFID/バーコードによるリアルタイム在庫追跡",
      "期限切れ・リコール対象品の自動アラート通知",
      "既存の院内システム（電子カルテ等）とのAPI連携が容易"
    ],
    "targetCustomer": "病院（200床以上）、医療機器ディーラー、医療機器メーカーの品質管理・物流部門。",
    "pricing": "初期導入費200万円〜、月額ライセンス15万円〜（管理デバイス数に応じた従量課金）",
    "caseStudies": [
      "総合病院C（500床）：導入後、医療機器の期限切れ廃棄ロスを年間1,200万円削減。監査対応時間も70%短縮。",
      "医療機器商社D：約8,000品目の在庫をリアルタイム可視化し、欠品による機会損失を年間800万円改善。"
    ],
    "differentiator": "国内の医療現場の運用フローに特化して設計されており、海外製の汎用トレーサビリティツールでは対応が難しい日本特有の法規制（薬機法改正、GS1コード対応等）をワンストップでカバー。導入支援チームが現場に常駐してセットアップを完了させる手厚いサポート体制。"
  },
  {
    "id": "product_c",
    "name": "GreenShift Analytics（カーボンニュートラル経営支援）",
    "category": "ESG / サステナビリティ",
    "summary": "企業のCO2排出量をScope1〜3まで自動計測し、削減シナリオのシミュレーションと投資家向けESGレポートの自動生成を行うプラットフォーム。",
    "strengths": [
      "経産省ガイドライン・GHGプロトコルに準拠した算定ロジック",
      "サプライチェーン全体（Scope3）の排出量を自動推計",
      "削減施策のROIシミュレーション機能",
      "TCFD/ISSB対応のレポートをワンクリック生成"
    ],
    "targetCustomer": "上場企業・上場準備企業のESG/サステナビリティ推進部門、IR部門。プライム市場企業を中心に、取引先からのScope3開示要請を受けている中堅企業。",
    "pricing": "年額360万円〜（従業員規模・拠点数に応じたプラン設計）",
    "caseStudies": [
      "上場メーカーE社：ESGレポート作成にかかる工数を年間400時間→40時間に削減。CDP評価がBからAマイナスに向上。",
      "食品メーカーF社：Scope3排出量の可視化により、調達先の切り替えで年間15%のCO2削減と年間2,000万円のコスト削減を同時達成。"
    ],
    "differentiator": "単なる『測定ツール』ではなく、『経営意思決定のための戦略プラットフォーム』として設計。削減と利益の両立を数値で示せるため、経営層への稟議が通りやすいのが最大の武器。専任のカーボンコンサルタントが導入から運用までハンズオン支援。"
  }
]
